{
  "variants": {
	"power=0": {
	  "model": "rpgcraftmodblock/light_provider"
	},
	"power=1": {
	  "model": "rpgcraftmodblock/light_provider"
	},
	"power=2": {
	  "model": "rpgcraftmodblock/light_provider"
	},
	"power=3": {
	  "model": "rpgcraftmodblock/light_provider"
	},
	"power=4": {
	  "model": "rpgcraftmodblock/light_provider"
	},
	"power=5": {
	  "model": "rpgcraftmodblock/light_provider"
	},
	"power=6": {
	  "model": "rpgcraftmodblock/light_provider"
	},
	"power=7": {
	  "model": "rpgcraftmodblock/light_provider"
	},
	"power=8": {
	  "model": "rpgcraftmodblock/light_provider"
	},
	"power=9": {
	  "model": "rpgcraftmodblock/light_provider"
	},
	"power=10": {
	  "model": "rpgcraftmodblock/light_provider"
	},
	"power=11": {
	  "model": "rpgcraftmodblock/light_provider"
	},
	"power=12": {
	  "model": "rpgcraftmodblock/light_provider"
	},
	"power=13": {
	  "model": "rpgcraftmodblock/light_provider"
	},
	"power=14": {
	  "model": "rpgcraftmodblock/light_provider"
	},
	"power=15": {
	  "model": "rpgcraftmodblock/light_provider"
	}
  }
}